dingo/MetabolicNetwork.py
dingo/PolytopeSampler.py
dingo/__init__.py
dingo/__main__.py
dingo/bindings/bindings.cpp
dingo/bindings/bindings.h
dingo/bindings/hmc_sampling.h
dingo/illustrations.py
dingo/loading_models.py
dingo/nullspace.py
dingo/parser.py
dingo/preprocess.py
dingo/pyoptinterface_based_impl.py
dingo/scaling.py
dingo/utils.py
dingo/volestipy.pyx
volestipy.cpython-310-x86_64-linux-gnu.so
dingo_walk/nullspace.py
dingo_walk/scaling.py
dingo_walk/loading_models.py
dingo_walk/PolytopeSampler.py
dingo_walk/utils.py
dingo_walk/parser.py
dingo_walk/MetabolicNetwork.py
dingo_walk/pyoptinterface_based_impl.py
dingo_walk/__init__.py
dingo_walk/preprocess.py
dingo_walk/illustrations.py
dingo_walk/__main__.py
dingo_walk-0.1.6.dist-info/METADATA
dingo_walk-0.1.6.dist-info/WHEEL
dingo_walk-0.1.6.dist-info/LICENSE
dingo_walk-0.1.6.dist-info/RECORD
